{
  "schema_version": "match-discovery-manifest.v1",
  "generated_at": "2026-06-16T01:19:32Z",
  "generated_for": {
    "local_date": "2026-06-16",
    "timezone": "America/Lima"
  },
  "search_window": {
    "from_utc": "2026-06-16T05:00:00Z",
    "to_utc": "2026-06-17T04:59:59Z"
  },
  "competition": {
    "id": "fifa-world-cup-2026",
    "name": "FIFA World Cup 2026",
    "season": "2026"
  },
  "matches": [
    {
      "candidate_key": "fifa-world-cup-2026-france-senegal-2026-06-16T19:00:00Z",
      "home_team": {
        "name": "France",
        "short_name": "FRA",
        "canonical_id": null
      },
      "away_team": {
        "name": "Senegal",
        "short_name": "SEN",
        "canonical_id": null
      },
      "stage": {
        "type": "group_stage",
        "name": "Group Stage",
        "group": "I",
        "matchday": 1
      },
      "venue": {
        "name": "New York New Jersey Stadium",
        "host_city": "New York/New Jersey",
        "country": "United States"
      },
      "kickoff": {
        "utc": "2026-06-16T19:00:00Z",
        "lima": "2026-06-16T14:00:00-05:00",
        "venue_local": "2026-06-16T15:00:00-04:00",
        "venue_timezone": "America/New_York"
      },
      "match_status": "scheduled",
      "monitoring_profile": "world_cup_market_and_stats_v1",
      "sources": {
        "schedule": [
          {
            "url": "https://www.fifa.com/en/tournaments/mens/worldcup/canadamexicousa2026/articles/france-senegal-preview-live-stream-team-news-tickets",
            "source_type": "official",
            "retrieved_at": "2026-06-16T01:19:32Z",
            "supports": [
              "competition",
              "teams",
              "kickoff",
              "venue",
              "stage"
            ],
            "confidence": 1.0
          }
        ],
        "stake": {
          "market": "PE",
          "locale": "es-PE",
          "discovery_status": "found",
          "event_url": "https://stake.pe/deportes/football/world/fifa-world-cup/francia-vs-senegal/event/21798335",
          "public_page_id": "21798335",
          "internal_event_id": null,
          "internal_endpoint": "https://pre-143o-sp.websbkt.com/cache/143/es/pe/21798335/single-pre-event.json?hidenseek=0fc410681c7e9dde40c657474e2859ff1385253d4634",
          "requires_browser_discovery": true,
          "confidence": 0.99
        },
        "espn": {
          "discovery_status": "found",
          "match_url": "https://espndeportes.espn.com/futbol/partido/_/juegoId/760432/senegal-francia",
          "event_id": "760432",
          "confidence": 0.99
        }
      },
      "validation": {
        "overall_confidence": 0.99,
        "review_required": false,
        "issues": []
      }
    },
    {
      "candidate_key": "fifa-world-cup-2026-iraq-norway-2026-06-16T22:00:00Z",
      "home_team": {
        "name": "Iraq",
        "short_name": "IRQ",
        "canonical_id": null
      },
      "away_team": {
        "name": "Norway",
        "short_name": "NOR",
        "canonical_id": null
      },
      "stage": {
        "type": "group_stage",
        "name": "Group Stage",
        "group": "I",
        "matchday": 1
      },
      "venue": {
        "name": "Boston Stadium",
        "host_city": "Boston",
        "country": "United States"
      },
      "kickoff": {
        "utc": "2026-06-16T22:00:00Z",
        "lima": "2026-06-16T17:00:00-05:00",
        "venue_local": "2026-06-16T18:00:00-04:00",
        "venue_timezone": "America/New_York"
      },
      "match_status": "scheduled",
      "monitoring_profile": "world_cup_market_and_stats_v1",
      "sources": {
        "schedule": [
          {
            "url": "https://www.fifa.com/en/tournaments/mens/worldcup/canadamexicousa2026/articles/iraq-norway-live-stream-team-news-tickets",
            "source_type": "official",
            "retrieved_at": "2026-06-16T01:19:32Z",
            "supports": [
              "competition",
              "teams",
              "kickoff",
              "venue",
              "stage"
            ],
            "confidence": 1.0
          }
        ],
        "stake": {
          "market": "PE",
          "locale": "es-PE",
          "discovery_status": "found",
          "event_url": "https://stake.pe/deportes/football/world/fifa-world-cup/irak-vs-noruega/event/24932192",
          "public_page_id": "24932192",
          "internal_event_id": null,
          "internal_endpoint": "https://pre-143o-sp.websbkt.com/cache/143/es/pe/24932192/single-pre-event.json?hidenseek=0fc458281c7e9dde40c657474e2859ff1385253d4634",
          "requires_browser_discovery": true,
          "confidence": 0.99
        },
        "espn": {
          "discovery_status": "found",
          "match_url": "https://espndeportes.espn.com/futbol/partido/_/juegoId/760430/noruega-irak",
          "event_id": "760430",
          "confidence": 0.99
        }
      },
      "validation": {
        "overall_confidence": 0.99,
        "review_required": false,
        "issues": []
      }
    },
    {
      "candidate_key": "fifa-world-cup-2026-argentina-algeria-2026-06-17T01:00:00Z",
      "home_team": {
        "name": "Argentina",
        "short_name": "ARG",
        "canonical_id": null
      },
      "away_team": {
        "name": "Algeria",
        "short_name": "DZA",
        "canonical_id": null
      },
      "stage": {
        "type": "group_stage",
        "name": "Group Stage",
        "group": "J",
        "matchday": 1
      },
      "venue": {
        "name": "Kansas City Stadium",
        "host_city": "Kansas City",
        "country": "United States"
      },
      "kickoff": {
        "utc": "2026-06-17T01:00:00Z",
        "lima": "2026-06-16T20:00:00-05:00",
        "venue_local": "2026-06-16T20:00:00-05:00",
        "venue_timezone": "America/Chicago"
      },
      "match_status": "scheduled",
      "monitoring_profile": "world_cup_market_and_stats_v1",
      "sources": {
        "schedule": [
          {
            "url": "https://www.fifa.com/en/tournaments/mens/worldcup/canadamexicousa2026/articles/argentina-algeria-preview-live-stream-team-news-tickets",
            "source_type": "official",
            "retrieved_at": "2026-06-16T01:19:32Z",
            "supports": [
              "competition",
              "teams",
              "kickoff",
              "venue",
              "stage"
            ],
            "confidence": 1.0
          }
        ],
        "stake": {
          "market": "PE",
          "locale": "es-PE",
          "discovery_status": "found",
          "event_url": "https://stake.pe/deportes/football/world/fifa-world-cup/argentina-vs-argelia/event/21798336",
          "public_page_id": "21798336",
          "internal_event_id": null,
          "internal_endpoint": "https://pre-143o-sp.websbkt.com/cache/143/es/pe/21798336/single-pre-event.json?hidenseek=0fc412681c7e9dde40c657474e2859ff1385253d4634",
          "requires_browser_discovery": true,
          "confidence": 0.99
        },
        "espn": {
          "discovery_status": "found",
          "match_url": "https://espndeportes.espn.com/futbol/partido/_/juegoId/760433/argelia-argentina",
          "event_id": "760433",
          "confidence": 0.99
        }
      },
      "validation": {
        "overall_confidence": 0.99,
        "review_required": false,
        "issues": [
          {
            "code": "utc_date_differs_from_lima_date",
            "severity": "info",
            "message": "El kickoff cae el 17 de junio en UTC, pero corresponde al 16 de junio a las 20:00 en America/Lima."
          }
        ]
      }
    },
    {
      "candidate_key": "fifa-world-cup-2026-austria-jordan-2026-06-17T04:00:00Z",
      "home_team": {
        "name": "Austria",
        "short_name": "AUT",
        "canonical_id": null
      },
      "away_team": {
        "name": "Jordan",
        "short_name": "JOR",
        "canonical_id": null
      },
      "stage": {
        "type": "group_stage",
        "name": "Group Stage",
        "group": "J",
        "matchday": 1
      },
      "venue": {
        "name": "San Francisco Bay Area Stadium",
        "host_city": "San Francisco Bay Area",
        "country": "United States"
      },
      "kickoff": {
        "utc": "2026-06-17T04:00:00Z",
        "lima": "2026-06-16T23:00:00-05:00",
        "venue_local": "2026-06-16T21:00:00-07:00",
        "venue_timezone": "America/Los_Angeles"
      },
      "match_status": "scheduled",
      "monitoring_profile": "world_cup_market_and_stats_v1",
      "sources": {
        "schedule": [
          {
            "url": "https://www.fifa.com/en/tournaments/mens/worldcup/canadamexicousa2026/articles/austria-jordan-live-stream-team-news-tickets-live-stream",
            "source_type": "official",
            "retrieved_at": "2026-06-16T01:19:32Z",
            "supports": [
              "competition",
              "teams",
              "kickoff",
              "venue",
              "stage"
            ],
            "confidence": 1.0
          }
        ],
        "stake": {
          "market": "PE",
          "locale": "es-PE",
          "discovery_status": "found",
          "event_url": "https://stake.pe/deportes/football/world/fifa-world-cup/austria-vs-jordania/event/21798334",
          "public_page_id": "21798334",
          "internal_event_id": null,
          "internal_endpoint": "https://pre-143o-sp.websbkt.com/cache/143/es/pe/21798334/single-pre-event.json?hidenseek=a2038678c2beab7e8e4628638abe5a5f2aeaddb32e04",
          "requires_browser_discovery": true,
          "confidence": 0.0
        },
        "espn": {
          "discovery_status": "found",
          "match_url": "https://espndeportes.espn.com/futbol/partido/_/juegoId/760431/jordania-austria",
          "event_id": "760431",
          "confidence": 0.99
        }
      },
      "validation": {
        "overall_confidence": 0.9,
        "review_required": false,
        "issues": [
          {
            "code": "provider_date_timezone_difference",
            "severity": "info",
            "message": "Algunos proveedores muestran el partido como 17 de junio porque el kickoff es 04:00 UTC. En America/Lima ocurre el 16 de junio a las 23:00."
          },
          {
            "code": "stake_pe_event_not_found",
            "severity": "warning",
            "message": "No se pudo confirmar una URL pública de Stake Perú para Austria vs Jordania. El orquestador debe intentar descubrirla nuevamente antes de programar la captura de cuotas."
          }
        ]
      }
    }
  ],
  "rejected_candidates": [],
  "summary": {
    "matches_discovered": 4,
    "matches_ready_for_orchestration": 3,
    "matches_requiring_review": 1,
    "stake_pages_found": 3,
    "stake_internal_endpoints_found": 0,
    "espn_pages_found": 4
  }
}